sumtools/__init__.py
sumtools/cli.py
sumtools/sumtools.py
sumtools-0.0.4.dist-info/LICENSE
sumtools-0.0.4.dist-info/METADATA
sumtools-0.0.4.dist-info/WHEEL
sumtools-0.0.4.dist-info/RECORD
